pecho/__init__.py
pecho/__init__.pyi
pecho-0.5.2.dist-info/LICENSE
pecho-0.5.2.dist-info/WHEEL
pecho-0.5.2.dist-info/METADATA
pecho-0.5.2.dist-info/RECORD
