Metadata-Version: 2.1
Name: pecho
Version: 0.5.2
Summary: Easy way to write things like status bars
Home-page: https://github.com/nihaals/pecho
License: MIT
Author: Nihaal Sangha
Author-email: me@niha.al
Requires-Python: >=3.6,<4.0
Classifier: License :: OSI Approved :: MIT License
Classifier: Programming Language :: Python :: 3
Classifier: Programming Language :: Python :: 3.6
Classifier: Programming Language :: Python :: 3.7
Classifier: Programming Language :: Python :: 3.8
Provides-Extra: windows
Requires-Dist: colorama (>=0.4.3,<0.5.0); extra == "windows"
Project-URL: Repository, https://github.com/nihaals/pecho
